odoo/addons/sale_disable_cancel_warning/README.rst
odoo/addons/sale_disable_cancel_warning/__init__.py
odoo/addons/sale_disable_cancel_warning/__manifest__.py
odoo/addons/sale_disable_cancel_warning/i18n/es.po
odoo/addons/sale_disable_cancel_warning/models/__init__.py
odoo/addons/sale_disable_cancel_warning/models/res_company.py
odoo/addons/sale_disable_cancel_warning/models/res_config_settings.py
odoo/addons/sale_disable_cancel_warning/models/sale_order.py
odoo/addons/sale_disable_cancel_warning/static/description/icon.png
odoo/addons/sale_disable_cancel_warning/views/res_config_settings.xml
odoo_addon_sale_disable_cancel_warning-16.0.1.0.0.5.dist-info/METADATA
odoo_addon_sale_disable_cancel_warning-16.0.1.0.0.5.dist-info/WHEEL
odoo_addon_sale_disable_cancel_warning-16.0.1.0.0.5.dist-info/top_level.txt
odoo_addon_sale_disable_cancel_warning-16.0.1.0.0.5.dist-info/RECORD
