Metadata-Version: 2.1
Name: odoo-addon-sale_disable_cancel_warning
Version: 16.0.1.0.0.5
Requires-Python: >=3.10
Requires-Dist: odoo>=16.0a,<16.1dev
Summary: Adds an option to disable the sale cancel warning wizard
Home-page: https://github.com/sygel-technology/sy-sale-workflow
License: AGPL-3
Author: =?utf-8?q?Alberto_Mart=C3=ADnez=2C_Odoo_Community_Association_=28OCA=29?=
Author-email: support@odoo-community.org
Classifier: Programming Language :: Python
Classifier: Framework :: Odoo
Classifier: Framework :: Odoo :: 16.0
Classifier: License :: OSI Approved :: GNU Affero General Public License v3
